profit/__init__.py
profit/agent.py
profit/clarifi.py
profit/clarifi_agent.py
profit/llama.py
profit/main.py
profit/tools.py
profit_pilot-0.2.8.dist-info/LICENSE
profit_pilot-0.2.8.dist-info/WHEEL
profit_pilot-0.2.8.dist-info/METADATA
profit_pilot-0.2.8.dist-info/RECORD
