Metadata-Version: 2.1
Name: profit-pilot
Version: 0.2.8
Summary: ProfitPilot - AI Agents
Home-page: https://github.com/kyegomez/ProfitPilot
License: MIT
Keywords: artificial intelligence,deep learning,optimizers,Prompt Engineering
Author: Kye Gomez
Author-email: kye@apac.ai
Requires-Python: >=3.6,<4.0
Classifier: Development Status :: 4 - Beta
Classifier: Intended Audience :: Developers
Classifier: License :: OSI Approved :: MIT License
Classifier: Programming Language :: Python :: 3
Classifier: Programming Language :: Python :: 3.6
Classifier: Programming Language :: Python :: 3.7
Classifier: Programming Language :: Python :: 3.8
Classifier: Programming Language :: Python :: 3.9
Classifier: Programming Language :: Python :: 3.10
Classifier: Programming Language :: Python :: 3.11
Classifier: Programming Language :: Python :: 3.6
Classifier: Topic :: Scientific/Engineering :: Artificial Intelligence
Requires-Dist: beautifulsoup4
Requires-Dist: clarifai
Requires-Dist: faiss-gpu (==1.7.2)
Requires-Dist: google-api-python-client
Requires-Dist: google-auth-httplib2
Requires-Dist: google-auth-oauthlib
Requires-Dist: langchain
Requires-Dist: langchain-experimental
Requires-Dist: openai
Requires-Dist: pandas
Requires-Dist: pydantic
Requires-Dist: torch
Requires-Dist: transformers
Project-URL: Repository, https://github.com/kyegomez/ProfitPilot
